drf_spectacular_auth/__init__.py
drf_spectacular_auth/apps.py
drf_spectacular_auth/backend.py
drf_spectacular_auth/conf.py
drf_spectacular_auth/middleware.py
drf_spectacular_auth/serializers.py
drf_spectacular_auth/urls.py
drf_spectacular_auth/views.py
drf_spectacular_auth/providers/__init__.py
drf_spectacular_auth/providers/base.py
drf_spectacular_auth/providers/cognito.py
drf_spectacular_auth/templates/drf_spectacular_auth/auth_panel.js
drf_spectacular_auth/templates/drf_spectacular_auth/swagger_ui.html
drf_spectacular_auth-1.4.2.dist-info/licenses/LICENSE
drf_spectacular_auth-1.4.2.dist-info/METADATA
drf_spectacular_auth-1.4.2.dist-info/WHEEL
drf_spectacular_auth-1.4.2.dist-info/top_level.txt
drf_spectacular_auth-1.4.2.dist-info/RECORD
