Metadata-Version: 2.4
Name: drf-spectacular-auth
Version: 1.4.2
Summary: Simple Authentication UI for DRF Spectacular with AWS Cognito integration and sessionStorage token management
Author-email: CodeMath <jadecon2655@gmail.com>
License: MIT
Project-URL: Homepage, https://github.com/CodeMath/drf-spectacular-auth
Project-URL: Repository, https://github.com/CodeMath/drf-spectacular-auth
Project-URL: Documentation, https://github.com/CodeMath/drf-spectacular-auth#readme
Project-URL: Bug Tracker, https://github.com/CodeMath/drf-spectacular-auth/issues
Keywords: django,drf,spectacular,swagger,cognito,auth,ui
Classifier: Development Status :: 4 - Beta
Classifier: Intended Audience :: Developers
Classifier: License :: OSI Approved :: MIT License
Classifier: Programming Language :: Python :: 3
Classifier: Programming Language :: Python :: 3.8
Classifier: Programming Language :: Python :: 3.9
Classifier: Programming Language :: Python :: 3.10
Classifier: Programming Language :: Python :: 3.11
Classifier: Programming Language :: Python :: 3.12
Classifier: Framework :: Django
Classifier: Framework :: Django :: 3.2
Classifier: Framework :: Django :: 4.0
Classifier: Framework :: Django :: 4.1
Classifier: Framework :: Django :: 4.2
Classifier: Framework :: Django :: 5.0
Classifier: Topic :: Internet :: WWW/HTTP
Classifier: Topic :: Software Development :: Libraries :: Python Modules
Requires-Python: >=3.8
License-File: LICENSE
Requires-Dist: Django>=3.2
Requires-Dist: djangorestframework>=3.12
Requires-Dist: drf-spectacular>=0.25.0
Requires-Dist: boto3>=1.20.0
Provides-Extra: dev
Requires-Dist: pytest>=6.0; extra == "dev"
Requires-Dist: pytest-django>=4.0; extra == "dev"
Requires-Dist: pytest-cov>=2.0; extra == "dev"
Requires-Dist: black>=22.0; extra == "dev"
Requires-Dist: isort>=5.0; extra == "dev"
Requires-Dist: flake8>=4.0; extra == "dev"
Dynamic: license-file
